IPP_Macro_Series_Parser-0.1.6.dist-info/DESCRIPTION.rst
IPP_Macro_Series_Parser-0.1.6.dist-info/METADATA
IPP_Macro_Series_Parser-0.1.6.dist-info/RECORD
IPP_Macro_Series_Parser-0.1.6.dist-info/WHEEL
IPP_Macro_Series_Parser-0.1.6.dist-info/entry_points.txt
IPP_Macro_Series_Parser-0.1.6.dist-info/metadata.json
IPP_Macro_Series_Parser-0.1.6.dist-info/top_level.txt
ipp_macro_series_parser/__init__.py
ipp_macro_series_parser/config.py
ipp_macro_series_parser/data_extraction.py
ipp_macro_series_parser/agregats_transports/__init__.py
ipp_macro_series_parser/agregats_transports/parser_cleaner_prix_carburants.py
ipp_macro_series_parser/agregats_transports/transports_cleaner.py
ipp_macro_series_parser/agregats_transports/transports_downloader.py
ipp_macro_series_parser/agregats_transports/transports_parser.py
ipp_macro_series_parser/agregats_transports/transports_tidy_data.py
ipp_macro_series_parser/agregats_transports/poids_carburants/__init__.py
ipp_macro_series_parser/agregats_transports/poids_carburants/parser_cleaner_prix_carburants.py
ipp_macro_series_parser/agregats_transports/poids_carburants/poids_carburants_cleaner.py
ipp_macro_series_parser/agregats_transports/poids_carburants/poids_carburants_downloader.py
ipp_macro_series_parser/agregats_transports/poids_carburants/poids_carburants_parser.py
ipp_macro_series_parser/comptes_nationaux/__init__.py
ipp_macro_series_parser/comptes_nationaux/cn_test.py
ipp_macro_series_parser/comptes_nationaux/generate_sheets.py
ipp_macro_series_parser/comptes_nationaux/get_file_infos.py
ipp_macro_series_parser/comptes_nationaux/output.py
ipp_macro_series_parser/comptes_nationaux/parser_main.py
ipp_macro_series_parser/comptes_nationaux/parser_non_tee.py
ipp_macro_series_parser/comptes_nationaux/parser_tee.py
ipp_macro_series_parser/comptes_nationaux/sheets_builder.py
ipp_macro_series_parser/comptes_nationaux/sheets_lists.py
ipp_macro_series_parser/demographie/__init__.py
ipp_macro_series_parser/demographie/build_parameters.py
ipp_macro_series_parser/demographie/dependance.py
ipp_macro_series_parser/demographie/parser.py
ipp_macro_series_parser/demographie/population.py
ipp_macro_series_parser/denombrements_fiscaux/__init__.py
ipp_macro_series_parser/denombrements_fiscaux/agregats_ipp.py
ipp_macro_series_parser/denombrements_fiscaux/denombrements_parsers.py
